asyncio_toolbox/__init__.py
asyncio_toolbox/_helpers.py
asyncio_toolbox/py.typed
asyncio_toolbox/tempfile.py
asyncio_toolbox/types.py
asyncio_toolbox/command_execution/__init__.py
asyncio_toolbox/command_execution/_base.py
asyncio_toolbox/command_execution/windows_command_wrapper.py
asyncio_toolbox-0.1.2.dist-info/METADATA
asyncio_toolbox-0.1.2.dist-info/WHEEL
asyncio_toolbox-0.1.2.dist-info/top_level.txt
asyncio_toolbox-0.1.2.dist-info/RECORD
